{"nodes": [{"id": "06_ai_wave2_3_audit", "label": "Audit 06 \u2014 AI Wave 2/3 Features", "file_type": "document", "source_file": "docs/audit/06-ai-wave2-3.md", "source_location": null, "source_url": null, "captured_at": "2026-05-20", "author": null, "contributor": null}, {"id": "concept_xray_no_writer", "label": "X-Ray table has no writer", "file_type": "rationale", "source_file": "docs/audit/06-ai-wave2-3.md", "source_location": null, "source_url": null, "captured_at": null, "author": null, "contributor": null}], "edges": [{"source": "06_ai_wave2_3_audit", "target": "06_plotexplainer", "relation": "references", "confidence": "EXTRACTED", "confidence_score": 1.0, "source_file": "docs/audit/06-ai-wave2-3.md", "source_location": null, "weight": 1.0}, {"source": "06_ai_wave2_3_audit", "target": "06_moviecomparator", "relation": "references", "confidence": "EXTRACTED", "confidence_score": 1.0, "source_file": "docs/audit/06-ai-wave2-3.md", "source_location": null, "weight": 1.0}, {"source": "06_ai_wave2_3_audit", "target": "06_soundtrackanalyzer", "relation": "references", "confidence": "EXTRACTED", "confidence_score": 1.0, "source_file": "docs/audit/06-ai-wave2-3.md", "source_location": null, "weight": 1.0}, {"source": "06_ai_wave2_3_audit", "target": "06_churnpredictor", "relation": "references", "confidence": "EXTRACTED", "confidence_score": 1.0, "source_file": "docs/audit/06-ai-wave2-3.md", "source_location": null, "weight": 1.0}, {"source": "06_ai_wave2_3_audit", "target": "06_xraycontroller", "relation": "references", "confidence": "EXTRACTED", "confidence_score": 1.0, "source_file": "docs/audit/06-ai-wave2-3.md", "source_location": null, "weight": 1.0}, {"source": "06_ai_wave2_3_audit", "target": "06_moviesceneactor_model", "relation": "references", "confidence": "EXTRACTED", "confidence_score": 1.0, "source_file": "docs/audit/06-ai-wave2-3.md", "source_location": null, "weight": 1.0}, {"source": "06_ai_wave2_3_audit", "target": "06_introoutrodetector", "relation": "references", "confidence": "EXTRACTED", "confidence_score": 1.0, "source_file": "docs/audit/06-ai-wave2-3.md", "source_location": null, "weight": 1.0}, {"source": "06_ai_wave2_3_audit", "target": "06_recapdetector", "relation": "references", "confidence": "EXTRACTED", "confidence_score": 1.0, "source_file": "docs/audit/06-ai-wave2-3.md", "source_location": null, "weight": 1.0}, {"source": "06_ai_wave2_3_audit", "target": "concept_xray_no_writer", "relation": "references", "confidence": "EXTRACTED", "confidence_score": 1.0, "source_file": "docs/audit/06-ai-wave2-3.md", "source_location": null, "weight": 1.0}, {"source": "06_xraycontroller", "target": "06_moviesceneactor_model", "relation": "calls", "confidence": "EXTRACTED", "confidence_score": 1.0, "source_file": "docs/audit/06-ai-wave2-3.md", "source_location": null, "weight": 1.0}, {"source": "concept_xray_no_writer", "target": "06_moviesceneactor_model", "relation": "references", "confidence": "EXTRACTED", "confidence_score": 1.0, "source_file": "docs/audit/06-ai-wave2-3.md", "source_location": null, "weight": 1.0}, {"source": "06_plotexplainer", "target": "05_ai_aiclient", "relation": "calls", "confidence": "EXTRACTED", "confidence_score": 1.0, "source_file": "docs/audit/06-ai-wave2-3.md", "source_location": null, "weight": 1.0}, {"source": "06_plotexplainer", "target": "05_ai_filmknowledgeservice", "relation": "calls", "confidence": "EXTRACTED", "confidence_score": 1.0, "source_file": "docs/audit/06-ai-wave2-3.md", "source_location": null, "weight": 1.0}, {"source": "06_recapdetector", "target": "06_introoutrodetector", "relation": "conceptually_related_to", "confidence": "EXTRACTED", "confidence_score": 0.9, "source_file": "docs/audit/06-ai-wave2-3.md", "source_location": null, "weight": 1.0}, {"source": "05_ai_wave1_audit", "target": "06_ai_wave2_3_audit", "relation": "conceptually_related_to", "confidence": "EXTRACTED", "confidence_score": 0.95, "source_file": "docs/audit/06-ai-wave2-3.md", "source_location": null, "weight": 1.0}], "hyperedges": []}